pkulaw_mcp_law_search/__init__.py
pkulaw_mcp_law_search/__main__.py
pkulaw_mcp_law_search/server.py
pkulaw_mcp_law_search-0.1.1.dist-info/METADATA
pkulaw_mcp_law_search-0.1.1.dist-info/WHEEL
pkulaw_mcp_law_search-0.1.1.dist-info/entry_points.txt
pkulaw_mcp_law_search-0.1.1.dist-info/RECORD
