Metadata-Version: 2.4
Name: pkulaw-mcp-law-search
Version: 0.1.1
Summary: PKULAW MCP server for law search
Author-email: PKULAW <fxtj@chinalawinfo.com>
License-Expression: MIT
Keywords: MCP server,PKULAW,law,legal,search
Classifier: Development Status :: 4 - Beta
Classifier: Intended Audience :: Developers
Classifier: Intended Audience :: Legal Industry
Classifier: License :: OSI Approved :: MIT License
Classifier: Operating System :: OS Independent
Classifier: Programming Language :: Python :: 3
Classifier: Programming Language :: Python :: 3.10
Requires-Python: >=3.10
Requires-Dist: fastmcp>=2.8.1
Requires-Dist: requests>=2.32.4
